sttcp/__init__.py
sttcp/client.py
sttcp/general.py
sttcp/server.py
simple_threaded_tcp-1.5.1.dist-info/METADATA
simple_threaded_tcp-1.5.1.dist-info/WHEEL
simple_threaded_tcp-1.5.1.dist-info/top_level.txt
simple_threaded_tcp-1.5.1.dist-info/RECORD
