Metadata-Version: 2.1
Name: simple_threaded_tcp
Version: 1.5.1
Summary: Client-Server threaded TCP connector. This project also uses socket library.
Author-email: Emil <emilahmaboy@gmail.com>
Project-URL: Homepage, https://github.com/EmilAhmaBoy/simple-threaded-tcp
Project-URL: Issues, https://github.com/EmilAhmaBoy/simple-threaded-tcp/issues
Classifier: Programming Language :: Python :: 3
Classifier: Operating System :: OS Independent
Requires-Python: >3.8
